[
  {
    "id_section": "1",
    "QA_section":[
      {
        "id_question": "1",
        "question_text": "question 1",
        "reponses_text": [
          {
            "id": "1",
            "text": "reponse A"
          },
          {
            "id": "2",
            "text": "reponse B"
          },
          {
            "id": "3",
            "text": "reponse C"
          },
          {
            "id": "4",
            "text": "reponse D"
          }
        ],
        "correct_answer_id": "2"
      },
      {
        "id_question": "2",
        "question_text": "question 2",
        "reponses_text": [
          {
            "id": "1",
            "text": "reponse A"
          },
          {
            "id": "2",
            "text": "reponse B"
          },
          {
            "id": "3",
            "text": "reponse C"
          },
          {
            "id": "4",
            "text": "reponse D"
          }
        ],
        "correct_answer_id": "3"
      }
    ]
  },
  {
    "id_section": "2",
    "QA_section":[
      {
        "id_question": "1",
        "question_text": "question 1",
        "reponses_text": [
          {
            "id": "1",
            "text": "reponse A"
          },
          {
            "id": "2",
            "text": "reponse B"
          },
          {
            "id": "3",
            "text": "reponse C"
          },
          {
            "id": "4",
            "text": "reponse D"
          }
        ],
        "correct_answer_id": "4"
      }
    ]
  },
  {
    "id_section": "3",
    "QA_section":[
      {
        "id_question": "1",
        "question_text": "question 1",
        "reponses_text": [
          {
            "id": "1",
            "text": "reponse A"
          },
          {
            "id": "2",
            "text": "reponse B"
          },
          {
            "id": "3",
            "text": "reponse C"
          },
          {
            "id": "4",
            "text": "reponse D"
          }
        ],
        "correct_answer_id": "3"
      }
    ]
  },
  {
    "id_section": "4",
    "QA_section":[
      {
        "id_question": "1",
        "question_text": "question 1",
        "reponses_text": [
          {
            "id": "1",
            "text": "reponse A"
          },
          {
            "id": "2",
            "text": "reponse B"
          },
          {
            "id": "3",
            "text": "reponse C"
          },
          {
            "id": "4",
            "text": "reponse D"
          }
        ],
        "correct_answer_id": "2"
      }
    ]
  },
  {
    "id_section": "5",
    "QA_section":[
      {
        "id_question": "1",
        "question_text": "question 1",
        "reponses_text": [
          {
            "id": "1",
            "text": "reponse A"
          },
          {
            "id": "2",
            "text": "reponse B"
          },
          {
            "id": "3",
            "text": "reponse C"
          },
          {
            "id": "4",
            "text": "reponse D"
          }
        ],
        "correct_answer_id": "1"
      }
    ]
  }
]